dj_vditor/__init__.py
dj_vditor/apps.py
dj_vditor/configs.py
dj_vditor/fields.py
dj_vditor/storage.py
dj_vditor/views.py
dj_vditor/widgets.py
dj_vditor/static/vditor/index.css
dj_vditor/static/vditor/index.min.js
dj_vditor/static/vditor/method.min.js
dj_vditor/static/vditor/css/content-theme/ant-design.css
dj_vditor/static/vditor/css/content-theme/dark.css
dj_vditor/static/vditor/css/content-theme/light.css
dj_vditor/static/vditor/css/content-theme/wechat.css
dj_vditor/static/vditor/images/.DS_Store
dj_vditor/static/vditor/images/img-loading.svg
dj_vditor/static/vditor/images/logo.png
dj_vditor/static/vditor/images/emoji/b3log.png
dj_vditor/static/vditor/images/emoji/chainbook.png
dj_vditor/static/vditor/images/emoji/doge.png
dj_vditor/static/vditor/images/emoji/hacpai.png
dj_vditor/static/vditor/images/emoji/huaji.gif
dj_vditor/static/vditor/images/emoji/latke.png
dj_vditor/static/vditor/images/emoji/lute.png
dj_vditor/static/vditor/images/emoji/octocat.png
dj_vditor/static/vditor/images/emoji/pipe.png
dj_vditor/static/vditor/images/emoji/solo.png
dj_vditor/static/vditor/images/emoji/sym.png
dj_vditor/static/vditor/images/emoji/trollface.png
dj_vditor/static/vditor/images/emoji/vditor.png
dj_vditor/static/vditor/images/emoji/wide.png
dj_vditor/static/vditor/images/emoji/wulian.png
dj_vditor/static/vditor/js/.DS_Store
dj_vditor/static/vditor/js/abcjs/abcjs_basic.min.js
dj_vditor/static/vditor/js/echarts/echarts.min.js
dj_vditor/static/vditor/js/flowchart.js/flowchart.min.js
dj_vditor/static/vditor/js/graphviz/full.render.js
dj_vditor/static/vditor/js/graphviz/viz.js
dj_vditor/static/vditor/js/highlight.js/highlight.pack.js
dj_vditor/static/vditor/js/highlight.js/styles/abap.css
dj_vditor/static/vditor/js/highlight.js/styles/algol.css
dj_vditor/static/vditor/js/highlight.js/styles/algol_nu.css
dj_vditor/static/vditor/js/highlight.js/styles/ant-design.css
dj_vditor/static/vditor/js/highlight.js/styles/arduino.css
dj_vditor_widget-0.3.5.dist-info/licenses/LICENSE
dj_vditor_widget-0.3.5.dist-info/METADATA
dj_vditor_widget-0.3.5.dist-info/WHEEL
dj_vditor_widget-0.3.5.dist-info/top_level.txt
dj_vditor_widget-0.3.5.dist-info/RECORD
