Metadata-Version: 2.4
Name: dj-vditor-widget
Version: 0.3.5
Summary: Django Textarea Widget Integrated Vditor with Customizable Configuration
Home-page: https://github.com/ren000thomas/dj-vditor-widget
Author: Ren Thomas
Author-email: ren000thomas@gmail.com
License: MIT
Classifier: Framework :: Django
Classifier: Programming Language :: Python :: 3
Classifier: License :: OSI Approved :: MIT License
License-File: LICENSE
Requires-Dist: Django>=4.0
Provides-Extra: oss
Requires-Dist: oss2>=2.15.0; extra == "oss"
Provides-Extra: tos
Requires-Dist: tos-python-sdk; extra == "tos"
Provides-Extra: all
Requires-Dist: oss2>=2.15.0; extra == "all"
Requires-Dist: tos-python-sdk; extra == "all"
Dynamic: author
Dynamic: author-email
Dynamic: classifier
Dynamic: description
Dynamic: description-content-type
Dynamic: home-page
Dynamic: license
Dynamic: license-file
Dynamic: provides-extra
Dynamic: requires-dist
Dynamic: summary
